LICENSE
MANIFEST.in
README.rst
setup.cfg
setup.py
Django_OnMyDesk.egg-info/SOURCES.txt
django_onmydesk.egg-info/PKG-INFO
django_onmydesk.egg-info/SOURCES.txt
django_onmydesk.egg-info/dependency_links.txt
django_onmydesk.egg-info/requires.txt
django_onmydesk.egg-info/top_level.txt
onmydesk/__init__.py
onmydesk/admin.py
onmydesk/managers.py
onmydesk/models.py
onmydesk/settings.py
onmydesk/utils.py
onmydesk/core/__init__.py
onmydesk/core/datasets.py
onmydesk/core/outputs.py
onmydesk/core/reports.py
onmydesk/forms/__init__.py
onmydesk/forms/fields.py
onmydesk/management/__init__.py
onmydesk/management/commands/__init__.py
onmydesk/management/commands/process.py
onmydesk/management/commands/scheduler_process.py
onmydesk/migrations/0001_initial.py
onmydesk/migrations/0002_auto_20160413_1435.py
onmydesk/migrations/0003_report_status.py
onmydesk/migrations/0004_auto_20160428_1503.py
onmydesk/migrations/0005_report_process_time.py
onmydesk/migrations/0006_report_params.py
onmydesk/migrations/0007_scheduler.py
onmydesk/migrations/0008_scheduler_notify_emails.py
onmydesk/migrations/0009_auto_20160516_1714.py
onmydesk/migrations/__init__.py
onmydesk/static/onmydesk/css/common.css
onmydesk/static/onmydesk/js/common.js
onmydesk/templates/onmydesk/scheduler-notify.html
onmydesk/templates/onmydesk/scheduler-notify.txt
onmydesk/tests/__init__.py
onmydesk/tests/test_commands.py
onmydesk/tests/test_core.py
onmydesk/tests/test_managers.py
onmydesk/tests/test_models.py
onmydesk/tests/test_utils.py