Metadata-Version: 1.1
Name: django-onmydesk
Version: 0.1.0
Summary: A simple Django app to build reports.
Home-page: https://github.com/knowledge4life/django-onmydesk/
Author: Alisson R. Perez
Author-email: alisson.perez@knowledge4.life
License: MIT License
Keywords: report,reporting,django
Platform: UNKNOWN
Classifier: Development Status :: 3 - Alpha
Classifier: Environment :: Web Environment
Classifier: Framework :: Django
Classifier: Intended Audience :: Developers
Classifier: License :: OSI Approved :: MIT License
Classifier: Operating System :: OS Independent
Classifier: Programming Language :: Python
Classifier: Programming Language :: Python :: 3
Classifier: Programming Language :: Python :: 3.4
Classifier: Topic :: Internet :: WWW/HTTP
Classifier: Topic :: Internet :: WWW/HTTP :: Dynamic Content
Classifier: Topic :: Office/Business :: Financial :: Spreadsheet
